{
    "draw_no": 1024,
    "draw_date": "2022-07-16",
    "winning_numbers": [
        9,
        18,
        20,
        22,
        38,
        44
    ],
    "bonus_number": 10,
    "rank_details": [
        {
            "rank": 1,
            "total_prize_amount": 24162588000,
            "num_winners": 8,
            "prize_per_game": 3020323500,
            "winning_criteria": "당첨번호 6개 숫자일치"
        },
        {
            "rank": 2,
            "total_prize_amount": 4027098033,
            "num_winners": 63,
            "prize_per_game": 63922191,
            "winning_criteria": "당첨번호 5개 숫자일치+보너스 숫자일치"
        },
        {
            "rank": 3,
            "total_prize_amount": 4027099176,
            "num_winners": 2616,
            "prize_per_game": 1539411,
            "winning_criteria": "당첨번호 5개 숫자일치"
        },
        {
            "rank": 4,
            "total_prize_amount": 6703250000,
            "num_winners": 134065,
            "prize_per_game": 50000,
            "winning_criteria": "당첨번호 4개 숫자일치"
        },
        {
            "rank": 5,
            "total_prize_amount": 11120485000,
            "num_winners": 2224097,
            "prize_per_game": 5000,
            "winning_criteria": "당첨번호 3개 숫자일치"
        }
    ],
    "note": "1등 자동7 수동1",
    "misc_info": {
        "payment_deadline": "지급개시일로부터 1년 (휴일인 경우 익영업일)",
        "total_sales_amount": 100081038000
    }
}