{
    "draw_no": 1147,
    "draw_date": "2024-11-23",
    "winning_numbers": [
        7,
        11,
        24,
        26,
        27,
        37
    ],
    "bonus_number": 32,
    "rank_details": [
        {
            "rank": 1,
            "total_prize_amount": 26587376632,
            "num_winners": 8,
            "prize_per_game": 3323422079,
            "winning_criteria": "당첨번호 6개 숫자일치"
        },
        {
            "rank": 2,
            "total_prize_amount": 4431229481,
            "num_winners": 83,
            "prize_per_game": 53388307,
            "winning_criteria": "당첨번호 5개 숫자일치+보너스 숫자일치"
        },
        {
            "rank": 3,
            "total_prize_amount": 4431230232,
            "num_winners": 3588,
            "prize_per_game": 1235014,
            "winning_criteria": "당첨번호 5개 숫자일치"
        },
        {
            "rank": 4,
            "total_prize_amount": 8651800000,
            "num_winners": 173036,
            "prize_per_game": 50000,
            "winning_criteria": "당첨번호 4개 숫자일치"
        },
        {
            "rank": 5,
            "total_prize_amount": 13751895000,
            "num_winners": 2750379,
            "prize_per_game": 5000,
            "winning_criteria": "당첨번호 3개 숫자일치"
        }
    ],
    "note": "1등 자동6 수동2",
    "misc_info": {
        "payment_deadline": "지급개시일로부터 1년 (휴일인 경우 익영업일)",
        "total_sales_amount": 115707061000
    }
}