{
    "draw_no": 465,
    "draw_date": "2011-10-29",
    "winning_numbers": [
        1,
        8,
        11,
        13,
        22,
        38
    ],
    "bonus_number": 31,
    "rank_details": [
        {
            "rank": 1,
            "total_prize_amount": 13465640251,
            "num_winners": 7,
            "prize_per_game": 1923662893,
            "winning_criteria": "당첨번호 6개 숫자일치"
        },
        {
            "rank": 2,
            "total_prize_amount": 2244273392,
            "num_winners": 46,
            "prize_per_game": 48788552,
            "winning_criteria": "당첨번호 5개 숫자일치+보너스 숫자일치"
        },
        {
            "rank": 3,
            "total_prize_amount": 2244274859,
            "num_winners": 1733,
            "prize_per_game": 1295023,
            "winning_criteria": "당첨번호 5개 숫자일치"
        },
        {
            "rank": 4,
            "total_prize_amount": 4162200000,
            "num_winners": 83244,
            "prize_per_game": 50000,
            "winning_criteria": "당첨번호 4개 숫자일치"
        },
        {
            "rank": 5,
            "total_prize_amount": 6780260000,
            "num_winners": 1356052,
            "prize_per_game": 5000,
            "winning_criteria": "당첨번호 3개 숫자일치"
        }
    ],
    "note": "1등 자동4 수동3",
    "misc_info": {
        "payment_deadline": "지급개시일로부터 1년 (휴일인 경우 익영업일)",
        "total_sales_amount": 57793294000
    }
}