{
    "draw_no": 810,
    "draw_date": "2018-06-09",
    "winning_numbers": [
        5,
        10,
        13,
        21,
        39,
        43
    ],
    "bonus_number": 11,
    "rank_details": [
        {
            "rank": 1,
            "total_prize_amount": 17852784376,
            "num_winners": 8,
            "prize_per_game": 2231598047,
            "winning_criteria": "당첨번호 6개 숫자일치"
        },
        {
            "rank": 2,
            "total_prize_amount": 2975464064,
            "num_winners": 64,
            "prize_per_game": 46491626,
            "winning_criteria": "당첨번호 5개 숫자일치+보너스 숫자일치"
        },
        {
            "rank": 3,
            "total_prize_amount": 2975464225,
            "num_winners": 2053,
            "prize_per_game": 1449325,
            "winning_criteria": "당첨번호 5개 숫자일치"
        },
        {
            "rank": 4,
            "total_prize_amount": 5030400000,
            "num_winners": 100608,
            "prize_per_game": 50000,
            "winning_criteria": "당첨번호 4개 숫자일치"
        },
        {
            "rank": 5,
            "total_prize_amount": 8360065000,
            "num_winners": 1672013,
            "prize_per_game": 5000,
            "winning_criteria": "당첨번호 3개 숫자일치"
        }
    ],
    "note": "1등 자동6 수동2",
    "misc_info": {
        "payment_deadline": "지급개시일로부터 1년 (휴일인 경우 익영업일)",
        "total_sales_amount": 74388355000
    }
}